{
  "openapi": "3.0.1",
  "info": {
    "title": "Presentation",
    "version": "1.0"
  },
  "paths": {
    "/api/v1/Admin/GetTenants": {
      "get": {
        "tags": [
          "Admin"
        ],
        "responses": {
          "200": {
            "description": "Success"
          }
        }
      }
    },
    "/api/v1/Admin/TenantDetails/{id}": {
      "get": {
        "tags": [
          "Admin"
        ],
        "parameters": [
          {
            "name": "id",
            "in": "path",
            "required": true,
            "schema": {
              "type": "string"
            }
          }
        ],
        "responses": {
          "200": {
            "description": "Success"
          }
        }
      }
    },
    "/api/v1/Admin/CreateTenantWithSoloDatabase": {
      "post": {
        "tags": [
          "Admin"
        ],
        "parameters": [
          {
            "name": "TenantName",
            "in": "header",
            "schema": {
              "type": "string"
            }
          },
          {
            "name": "ConnectionString",
            "in": "header",
            "schema": {
              "type": "string"
            }
          }
        ],
        "responses": {
          "200": {
            "description": "Success"
          }
        }
      }
    },
    "/api/v1/Admin/CreateTenantWithSharedDb": {
      "post": {
        "tags": [
          "Admin"
        ],
        "parameters": [
          {
            "name": "tenantName",
            "in": "query",
            "required": true,
            "schema": {
              "type": "string"
            }
          }
        ],
        "responses": {
          "200": {
            "description": "Success"
          }
        }
      }
    },
    "/api/v1/Admin/DeleteTenantWithSharedDb": {
      "delete": {
        "tags": [
          "Admin"
        ],
        "parameters": [
          {
            "name": "TenantId",
            "in": "header",
            "schema": {
              "type": "string"
            }
          }
        ],
        "responses": {
          "200": {
            "description": "Success"
          }
        }
      }
    },
    "/api/v1/Admin/DeleteTenantWithSoloDb": {
      "delete": {
        "tags": [
          "Admin"
        ],
        "parameters": [
          {
            "name": "TenantId",
            "in": "header",
            "schema": {
              "type": "string"
            }
          }
        ],
        "responses": {
          "200": {
            "description": "Success"
          }
        }
      }
    },
    "/api/v1/Admin/Branch/{id}": {
      "get": {
        "tags": [
          "Admin"
        ],
        "parameters": [
          {
            "name": "id",
            "in": "path",
            "required": true,
            "schema": {
              "type": "string"
            }
          }
        ],
        "responses": {
          "200": {
            "description": "Success"
          }
        }
      }
    },
    "/api/v1/Admin/CreateNewBranch": {
      "post": {
        "tags": [
          "Admin"
        ],
        "requestBody": {
          "content": {
            "application/json": {
              "schema": {
                "$ref": "#/components/schemas/CreateBranchCommand"
              }
            },
            "text/json": {
              "schema": {
                "$ref": "#/components/schemas/CreateBranchCommand"
              }
            },
            "application/*+json": {
              "schema": {
                "$ref": "#/components/schemas/CreateBranchCommand"
              }
            }
          }
        },
        "responses": {
          "200": {
            "description": "Success"
          }
        }
      }
    },
    "/api/v1/Admin/DeleteBranch/{id}": {
      "delete": {
        "tags": [
          "Admin"
        ],
        "parameters": [
          {
            "name": "id",
            "in": "path",
            "required": true,
            "schema": {
              "type": "string"
            }
          }
        ],
        "responses": {
          "200": {
            "description": "Success"
          }
        }
      }
    },
    "/api/v1/Admin/CreateBranchAdmin": {
      "post": {
        "tags": [
          "Admin"
        ],
        "parameters": [
          {
            "name": "TenantId",
            "in": "header",
            "schema": {
              "type": "string"
            }
          },
          {
            "name": "BranchId",
            "in": "header",
            "schema": {
              "type": "string"
            }
          }
        ],
        "requestBody": {
          "content": {
            "application/json": {
              "schema": {
                "$ref": "#/components/schemas/CreateBranchAdminCommand"
              }
            },
            "text/json": {
              "schema": {
                "$ref": "#/components/schemas/CreateBranchAdminCommand"
              }
            },
            "application/*+json": {
              "schema": {
                "$ref": "#/components/schemas/CreateBranchAdminCommand"
              }
            }
          }
        },
        "responses": {
          "200": {
            "description": "Success"
          }
        }
      }
    },
    "/api/v1/Authentication/signin": {
      "post": {
        "tags": [
          "Authentication"
        ],
        "requestBody": {
          "content": {
            "application/json": {
              "schema": {
                "$ref": "#/components/schemas/SignInCommand"
              }
            },
            "text/json": {
              "schema": {
                "$ref": "#/components/schemas/SignInCommand"
              }
            },
            "application/*+json": {
              "schema": {
                "$ref": "#/components/schemas/SignInCommand"
              }
            }
          }
        },
        "responses": {
          "200": {
            "description": "Success"
          }
        }
      }
    },
    "/api/v1/Authentication/logout": {
      "post": {
        "tags": [
          "Authentication"
        ],
        "responses": {
          "200": {
            "description": "Success"
          }
        }
      }
    },
    "/api/v1/Authentication/refreshtoken": {
      "post": {
        "tags": [
          "Authentication"
        ],
        "responses": {
          "200": {
            "description": "Success"
          }
        }
      }
    },
    "/api/v1/Authentication/Profile/{id}": {
      "get": {
        "tags": [
          "Authentication"
        ],
        "parameters": [
          {
            "name": "id",
            "in": "path",
            "required": true,
            "schema": {
              "type": "string"
            }
          }
        ],
        "responses": {
          "200": {
            "description": "Success"
          }
        }
      }
    },
    "/api/v1/BranchAdmin/createrequester": {
      "post": {
        "tags": [
          "BranchAdmin"
        ],
        "requestBody": {
          "content": {
            "application/json": {
              "schema": {
                "$ref": "#/components/schemas/CreateRequesterCommand"
              }
            },
            "text/json": {
              "schema": {
                "$ref": "#/components/schemas/CreateRequesterCommand"
              }
            },
            "application/*+json": {
              "schema": {
                "$ref": "#/components/schemas/CreateRequesterCommand"
              }
            }
          }
        },
        "responses": {
          "200": {
            "description": "Success"
          }
        }
      }
    },
    "/api/v1/BranchAdmin/createmanager": {
      "post": {
        "tags": [
          "BranchAdmin"
        ],
        "requestBody": {
          "content": {
            "application/json": {
              "schema": {
                "$ref": "#/components/schemas/CreateManagerCommand"
              }
            },
            "text/json": {
              "schema": {
                "$ref": "#/components/schemas/CreateManagerCommand"
              }
            },
            "application/*+json": {
              "schema": {
                "$ref": "#/components/schemas/CreateManagerCommand"
              }
            }
          }
        },
        "responses": {
          "200": {
            "description": "Success"
          }
        }
      }
    },
    "/api/v1/BranchAdmin/createsecurity": {
      "post": {
        "tags": [
          "BranchAdmin"
        ],
        "requestBody": {
          "content": {
            "application/json": {
              "schema": {
                "$ref": "#/components/schemas/CreateSecurityCommand"
              }
            },
            "text/json": {
              "schema": {
                "$ref": "#/components/schemas/CreateSecurityCommand"
              }
            },
            "application/*+json": {
              "schema": {
                "$ref": "#/components/schemas/CreateSecurityCommand"
              }
            }
          }
        },
        "responses": {
          "200": {
            "description": "Success"
          }
        }
      }
    },
    "/api/v1/BranchAdmin/deletemanager/{id}": {
      "delete": {
        "tags": [
          "BranchAdmin"
        ],
        "parameters": [
          {
            "name": "id",
            "in": "path",
            "required": true,
            "schema": {
              "type": "string"
            }
          }
        ],
        "responses": {
          "200": {
            "description": "Success"
          }
        }
      }
    },
    "/api/v1/BranchAdmin/deleterequester/{id}": {
      "delete": {
        "tags": [
          "BranchAdmin"
        ],
        "parameters": [
          {
            "name": "id",
            "in": "path",
            "required": true,
            "schema": {
              "type": "string"
            }
          }
        ],
        "responses": {
          "200": {
            "description": "Success"
          }
        }
      }
    },
    "/api/v1/BranchAdmin/deletesecurity/{id}": {
      "delete": {
        "tags": [
          "BranchAdmin"
        ],
        "parameters": [
          {
            "name": "id",
            "in": "path",
            "required": true,
            "schema": {
              "type": "string"
            }
          }
        ],
        "responses": {
          "200": {
            "description": "Success"
          }
        }
      }
    },
    "/api/v1/Permit/{id}": {
      "get": {
        "tags": [
          "Permit"
        ],
        "parameters": [
          {
            "name": "id",
            "in": "path",
            "required": true,
            "schema": {
              "type": "string"
            }
          }
        ],
        "responses": {
          "200": {
            "description": "Success"
          }
        }
      },
      "delete": {
        "tags": [
          "Permit"
        ],
        "parameters": [
          {
            "name": "id",
            "in": "path",
            "required": true,
            "schema": {
              "type": "string"
            }
          }
        ],
        "responses": {
          "200": {
            "description": "Success"
          }
        }
      }
    },
    "/api/v1/Permit/{id}/details": {
      "get": {
        "tags": [
          "Permit"
        ],
        "parameters": [
          {
            "name": "id",
            "in": "path",
            "required": true,
            "schema": {
              "type": "string"
            }
          }
        ],
        "responses": {
          "200": {
            "description": "Success"
          }
        }
      }
    },
    "/api/v1/Permit": {
      "get": {
        "tags": [
          "Permit"
        ],
        "responses": {
          "200": {
            "description": "Success"
          }
        }
      },
      "post": {
        "tags": [
          "Permit"
        ],
        "requestBody": {
          "content": {
            "multipart/form-data": {
              "schema": {
                "type": "object",
                "properties": {
                  "StartDate": {
                    "type": "string",
                    "format": "date-time"
                  },
                  "EndDate": {
                    "type": "string",
                    "format": "date-time"
                  },
                  "Reason": {
                    "type": "string"
                  },
                  "BuildingId": {
                    "type": "string"
                  },
                  "FloorNumber": {
                    "type": "integer",
                    "format": "int32"
                  },
                  "BelongingDtos": {
                    "type": "array",
                    "items": {
                      "$ref": "#/components/schemas/CreateBelonging"
                    }
                  },
                  "Attachments": {
                    "type": "array",
                    "items": {
                      "$ref": "#/components/schemas/CreateAttachment"
                    }
                  },
                  "VisitorId": {
                    "type": "string"
                  }
                }
              },
              "encoding": {
                "StartDate": {
                  "style": "form"
                },
                "EndDate": {
                  "style": "form"
                },
                "Reason": {
                  "style": "form"
                },
                "BuildingId": {
                  "style": "form"
                },
                "FloorNumber": {
                  "style": "form"
                },
                "BelongingDtos": {
                  "style": "form"
                },
                "Attachments": {
                  "style": "form"
                },
                "VisitorId": {
                  "style": "form"
                }
              }
            }
          }
        },
        "responses": {
          "200": {
            "description": "Success"
          }
        }
      }
    },
    "/api/v1/Permit/paginate": {
      "get": {
        "tags": [
          "Permit"
        ],
        "requestBody": {
          "content": {
            "application/json": {
              "schema": {
                "$ref": "#/components/schemas/PaginatePermits"
              }
            },
            "text/json": {
              "schema": {
                "$ref": "#/components/schemas/PaginatePermits"
              }
            },
            "application/*+json": {
              "schema": {
                "$ref": "#/components/schemas/PaginatePermits"
              }
            }
          }
        },
        "responses": {
          "200": {
            "description": "Success"
          }
        }
      }
    },
    "/api/v1/Permit/requester/{requesterId}": {
      "get": {
        "tags": [
          "Permit"
        ],
        "parameters": [
          {
            "name": "requesterId",
            "in": "path",
            "required": true,
            "schema": {
              "type": "string"
            }
          }
        ],
        "responses": {
          "200": {
            "description": "Success"
          }
        }
      }
    },
    "/api/v1/Permit/manager/{managerId}": {
      "get": {
        "tags": [
          "Permit"
        ],
        "parameters": [
          {
            "name": "managerId",
            "in": "path",
            "required": true,
            "schema": {
              "type": "string"
            }
          }
        ],
        "responses": {
          "200": {
            "description": "Success"
          }
        }
      }
    },
    "/api/v1/Permit/visitor/{visitorId}": {
      "get": {
        "tags": [
          "Permit"
        ],
        "parameters": [
          {
            "name": "visitorId",
            "in": "path",
            "required": true,
            "schema": {
              "type": "string"
            }
          }
        ],
        "responses": {
          "200": {
            "description": "Success"
          }
        }
      }
    },
    "/api/v1/Permit/latest": {
      "get": {
        "tags": [
          "Permit"
        ],
        "parameters": [
          {
            "name": "count",
            "in": "query",
            "schema": {
              "type": "integer",
              "format": "int32"
            }
          }
        ],
        "responses": {
          "200": {
            "description": "Success"
          }
        }
      }
    },
    "/api/v1/Permit/searchbydate": {
      "get": {
        "tags": [
          "Permit"
        ],
        "parameters": [
          {
            "name": "startDate",
            "in": "query",
            "schema": {
              "type": "string",
              "format": "date-time"
            }
          },
          {
            "name": "endDate",
            "in": "query",
            "schema": {
              "type": "string",
              "format": "date-time"
            }
          }
        ],
        "responses": {
          "200": {
            "description": "Success"
          }
        }
      }
    },
    "/api/v1/Permit/{id}/entrylog": {
      "get": {
        "tags": [
          "Permit"
        ],
        "parameters": [
          {
            "name": "id",
            "in": "path",
            "required": true,
            "schema": {
              "type": "string"
            }
          }
        ],
        "responses": {
          "200": {
            "description": "Success"
          }
        }
      }
    },
    "/api/v1/Permit/{id}/history": {
      "get": {
        "tags": [
          "Permit"
        ],
        "parameters": [
          {
            "name": "id",
            "in": "path",
            "required": true,
            "schema": {
              "type": "string"
            }
          }
        ],
        "responses": {
          "200": {
            "description": "Success"
          }
        }
      }
    },
    "/api/v1/Permit/{id}/approve": {
      "patch": {
        "tags": [
          "Permit"
        ],
        "parameters": [
          {
            "name": "id",
            "in": "path",
            "required": true,
            "schema": {
              "type": "string"
            }
          }
        ],
        "responses": {
          "200": {
            "description": "Success"
          }
        }
      }
    },
    "/api/v1/Permit/{id}/reject": {
      "patch": {
        "tags": [
          "Permit"
        ],
        "parameters": [
          {
            "name": "id",
            "in": "path",
            "required": true,
            "schema": {
              "type": "string"
            }
          }
        ],
        "responses": {
          "200": {
            "description": "Success"
          }
        }
      }
    },
    "/api/v1/Permit/extend": {
      "patch": {
        "tags": [
          "Permit"
        ],
        "requestBody": {
          "content": {
            "application/json": {
              "schema": {
                "$ref": "#/components/schemas/ExtendPermitCommand"
              }
            },
            "text/json": {
              "schema": {
                "$ref": "#/components/schemas/ExtendPermitCommand"
              }
            },
            "application/*+json": {
              "schema": {
                "$ref": "#/components/schemas/ExtendPermitCommand"
              }
            }
          }
        },
        "responses": {
          "200": {
            "description": "Success"
          }
        }
      }
    }
  },
  "components": {
    "schemas": {
      "CreateAttachment": {
        "type": "object",
        "properties": {
          "type": {
            "type": "string",
            "nullable": true
          },
          "file": {
            "type": "string",
            "format": "binary",
            "nullable": true
          }
        },
        "additionalProperties": false
      },
      "CreateBelonging": {
        "type": "object",
        "properties": {
          "name": {
            "type": "string",
            "nullable": true
          },
          "description": {
            "type": "string",
            "nullable": true
          },
          "plateNumber": {
            "type": "string",
            "nullable": true
          },
          "color": {
            "type": "string",
            "nullable": true
          }
        },
        "additionalProperties": false
      },
      "CreateBranchAdminCommand": {
        "type": "object",
        "properties": {
          "firstName": {
            "type": "string",
            "nullable": true
          },
          "lastName": {
            "type": "string",
            "nullable": true
          },
          "email": {
            "type": "string",
            "nullable": true
          },
          "password": {
            "type": "string",
            "nullable": true
          },
          "confirmPassword": {
            "type": "string",
            "nullable": true
          },
          "phoneNumber": {
            "type": "string",
            "nullable": true
          },
          "gender": {
            "$ref": "#/components/schemas/PersonGender"
          }
        },
        "additionalProperties": false
      },
      "CreateBranchCommand": {
        "type": "object",
        "properties": {
          "branchName": {
            "type": "string",
            "nullable": true
          },
          "country": {
            "type": "string",
            "nullable": true
          },
          "city": {
            "type": "string",
            "nullable": true
          },
          "street": {
            "type": "string",
            "nullable": true
          },
          "phoneNumber": {
            "type": "string",
            "nullable": true
          },
          "email": {
            "type": "string",
            "nullable": true
          }
        },
        "additionalProperties": false
      },
      "CreateManagerCommand": {
        "type": "object",
        "properties": {
          "firstName": {
            "type": "string",
            "nullable": true
          },
          "lastName": {
            "type": "string",
            "nullable": true
          },
          "email": {
            "type": "string",
            "nullable": true
          },
          "password": {
            "type": "string",
            "nullable": true
          },
          "confirmPassword": {
            "type": "string",
            "nullable": true
          },
          "phoneNumber": {
            "type": "string",
            "nullable": true
          },
          "gender": {
            "$ref": "#/components/schemas/PersonGender"
          }
        },
        "additionalProperties": false
      },
      "CreateRequesterCommand": {
        "type": "object",
        "properties": {
          "firstName": {
            "type": "string",
            "nullable": true
          },
          "lastName": {
            "type": "string",
            "nullable": true
          },
          "email": {
            "type": "string",
            "nullable": true
          },
          "password": {
            "type": "string",
            "nullable": true
          },
          "confirmPassword": {
            "type": "string",
            "nullable": true
          },
          "phoneNumber": {
            "type": "string",
            "nullable": true
          },
          "gender": {
            "$ref": "#/components/schemas/PersonGender"
          }
        },
        "additionalProperties": false
      },
      "CreateSecurityCommand": {
        "type": "object",
        "properties": {
          "firstName": {
            "type": "string",
            "nullable": true
          },
          "lastName": {
            "type": "string",
            "nullable": true
          },
          "email": {
            "type": "string",
            "nullable": true
          },
          "password": {
            "type": "string",
            "nullable": true
          },
          "confirmPassword": {
            "type": "string",
            "nullable": true
          },
          "phoneNumber": {
            "type": "string",
            "nullable": true
          },
          "gender": {
            "$ref": "#/components/schemas/PersonGender"
          }
        },
        "additionalProperties": false
      },
      "ExtendPermitCommand": {
        "type": "object",
        "properties": {
          "permitId": {
            "type": "string",
            "nullable": true
          },
          "newEndDate": {
            "type": "string",
            "format": "date-time"
          }
        },
        "additionalProperties": false
      },
      "PaginatePermits": {
        "type": "object",
        "properties": {
          "id": {
            "type": "string",
            "nullable": true
          },
          "cursorDate": {
            "type": "string",
            "format": "date-time",
            "nullable": true
          },
          "direction": {
            "$ref": "#/components/schemas/PaginationDirection"
          }
        },
        "additionalProperties": false
      },
      "PaginationDirection": {
        "enum": [
          1,
          -1
        ],
        "type": "integer",
        "format": "int32"
      },
      "PersonGender": {
        "enum": [
          0,
          1
        ],
        "type": "integer",
        "format": "int32"
      },
      "SignInCommand": {
        "type": "object",
        "properties": {
          "email": {
            "type": "string",
            "nullable": true
          },
          "password": {
            "type": "string",
            "nullable": true
          }
        },
        "additionalProperties": false
      }
    }
  }
}